ThreeDJCG/__init__.py
ThreeDJCG/app.py
ThreeDJCG/crash_on_ipy.py
ThreeDJCG/download-scannet.py
ThreeDJCG/model.py
ThreeDJCG/data/__init__.py
ThreeDJCG/data/scannet/__init__.py
ThreeDJCG/data/scannet/batch_load_scannet_data.py
ThreeDJCG/data/scannet/load_scannet_data.py
ThreeDJCG/data/scannet/model_util_scannet.py
ThreeDJCG/data/scannet/scannet_utils.py
ThreeDJCG/data/scannet/visualize.py
ThreeDJCG/data/scannet/meta_data/__init__.py
ThreeDJCG/lib/__init__.py
ThreeDJCG/lib/ap_helper.py
ThreeDJCG/lib/ap_helper_fcos.py
ThreeDJCG/lib/config.py
ThreeDJCG/lib/config_captioning.py
ThreeDJCG/lib/config_grounding.py
ThreeDJCG/lib/config_joint.py
ThreeDJCG/lib/config_vqa.py
ThreeDJCG/lib/capeval/__init__.py
ThreeDJCG/lib/capeval/bleu/__init__.py
ThreeDJCG/lib/capeval/bleu/bleu.py
ThreeDJCG/lib/capeval/bleu/bleu_scorer.py
ThreeDJCG/lib/capeval/cider/__init__.py
ThreeDJCG/lib/capeval/cider/cider.py
ThreeDJCG/lib/capeval/cider/cider_scorer.py
ThreeDJCG/lib/capeval/meteor/__init__.py
ThreeDJCG/lib/capeval/meteor/meteor.py
ThreeDJCG/lib/capeval/rouge/__init__.py
ThreeDJCG/lib/capeval/rouge/rouge.py
ThreeDJCG/lib/joint/__init__.py
ThreeDJCG/lib/joint/dataset.py
ThreeDJCG/lib/joint/eval_caption.py
ThreeDJCG/lib/joint/eval_ground.py
ThreeDJCG/lib/joint/solver.py
ThreeDJCG/lib/loss_helper/__init__.py
ThreeDJCG/lib/loss_helper/loss.py
ThreeDJCG/lib/loss_helper/loss_captioning.py
ThreeDJCG/lib/loss_helper/loss_detection.py
ThreeDJCG/lib/loss_helper/loss_grounding.py
ThreeDJCG/lib/loss_helper/loss_joint.py
ThreeDJCG/lib/loss_helper/loss_vqa.py
ThreeDJCG/lib/pointnet2/__init__.py
ThreeDJCG/lib/pointnet2/pointnet2_modules.py
ThreeDJCG/lib/pointnet2/pointnet2_utils.py
ThreeDJCG/lib/pointnet2/pytorch_utils.py
ThreeDJCG/lib/pointnet2/setup.py
ThreeDJCG/lib/visual_captioning/__init__.py
ThreeDJCG/lib/visual_captioning/dataset.py
ThreeDJCG/lib/visual_captioning/enet.py
ThreeDJCG/lib/visual_captioning/eval_helper.py
ThreeDJCG/lib/visual_captioning/solver.py
ThreeDJCG-0.1.14.dist-info/METADATA
ThreeDJCG-0.1.14.dist-info/WHEEL
ThreeDJCG-0.1.14.dist-info/top_level.txt
ThreeDJCG-0.1.14.dist-info/RECORD
