Metadata-Version: 2.1
Name: ThreeDJCG
Version: 0.1.14
Summary: Joint Captioning and Grounding
Home-page: https://github.com/ScaryJellyfish/ThreeDJCG
Author: Rui Zheng
Author-email: 1156486807@qq.com
License: UNKNOWN
Download-URL: https://github.com/ScaryJellyfish/ThreeDJCG/tags
Platform: UNKNOWN
Requires-Python: >=3.7
Requires-Dist: pillow
Requires-Dist: aiofiles
Requires-Dist: fastapi
Requires-Dist: uvicorn[standard]
Requires-Dist: python-multipart
Requires-Dist: ftfy
Requires-Dist: regex
Requires-Dist: tqdm
Requires-Dist: h5py
Requires-Dist: easydict
